django_enterprise/__init__.py
django_enterprise/apps.py
django_enterprise-0.0.1.dist-info/METADATA
django_enterprise-0.0.1.dist-info/WHEEL
django_enterprise-0.0.1.dist-info/RECORD
